[
  {
    "Rozdil": "Історія",
    "Tekst": "У якому році відбулася Хрещення Русі?",
    "Varianty": [ "988", "998", "878", "1015" ],
    "PravylnyIndex": [ 0 ]
  },
  {
    "Rozdil": "Історія",
    "Tekst": "Хто був першим князем Київської Русі?",
    "Varianty": [ "Олег", "Ігор", "Рюрик", "Володимир" ],
    "PravylnyIndex": [ 2 ]
  },
  {
    "Rozdil": "Історія",
    "Tekst": "Які битви відбулися під час Другої світової війни?",
    "Varianty": [ "Сталінградська", "Курська", "Полтавська", "Грюнвальдська" ],
    "PravylnyIndex": [ 0, 1 ]
  },
  {
    "Rozdil": "Географія",
    "Tekst": "Яка найдовша річка в Україні?",
    "Varianty": [ "Дніпро", "Дунай", "Дністер", "Південний Буг" ],
    "PravylnyIndex": [ 0 ]
  },
  {
    "Rozdil": "Географія",
    "Tekst": "Які країни межують з Україною?",
    "Varianty": [ "Польща", "Румунія", "Німеччина", "Словаччина" ],
    "PravylnyIndex": [ 0, 1, 3 ]
  },
  {
    "Rozdil": "Біологія",
    "Tekst": "Які організми відносяться до еукаріотів?",
    "Varianty": [ "Тварини", "Бактерії", "Рослини", "Гриби" ],
    "PravylnyIndex": [ 0, 2, 3 ]
  }
]